{
  "pokemon": "espeon",
  "learnset": {
    "allyswitch": ["8M", "7T"],
    "attract": ["8M", "7M", "7V", "6M", "5M", "4M", "3M"],
    "babydolleyes": ["8L15", "7L9"],
    "batonpass": ["8M", "8L1"],
    "bite": ["8L1"],
    "bodyslam": ["8M", "3T"],
    "calmmind": ["8M", "7M", "6M", "5M", "4M", "3M"],
    "captivate": ["4M"],
    "celebrate": ["6S2"],
    "charm": ["8M", "8L1"],
    "confide": ["7M", "6M"],
    "confusion": ["8L0", "7L1", "7V", "6L9", "6S2", "5L15", "4L15", "3L16"],
    "copycat": ["8L1"],
    "covet": ["8L1", "7T", "6T", "5T"],
    "curse": ["7V"],
    "cut": ["7V", "6M", "5M", "4M", "3M"],
    "dazzlinggleam": ["8M", "7M", "7S3", "6M"],
    "detect": ["7V"],
    "dig": ["8M", "6M", "5M", "4M", "3M"],
    "doubleedge": ["8L1", "3T"],
    "doubleteam": ["7M", "7V", "6M", "5M", "4M", "3M"],
    "dreameater": ["7M", "7V", "6M", "5M", "4M", "3T"],
    "echoedvoice": ["7M", "6M", "5M"],
    "endure": ["8M", "7V", "4M", "3T"],
    "expandingforce": ["8T"],
    "facade": ["8M", "7M", "6M", "5M", "4M", "3M"],
    "faketears": ["8M"],
    "flash": ["7V", "6M", "5M", "4M", "3M"],
    "focusenergy": ["8M"],
    "frustration": ["7M", "7V", "6M", "5M", "4M", "3M"],
    "futuresight": ["8M", "8L50", "7L25", "6L25", "5L43", "4L43"],
    "gigaimpact": ["8M", "7M", "6M", "5M", "4M"],
    "grassknot": ["8M", "7M", "6M", "5M", "4M"],
    "growl": ["8L1"],
    "headbutt": ["7V", "4T"],
    "healbell": ["7T", "6T", "5T", "4T"],
    "helpinghand": [
      "8M",
      "8L1",
      "7T",
      "7L1",
      "6T",
      "6L1",
      "5T",
      "5L1",
      "5S1",
      "4T",
      "4L1",
      "3L1"
    ],
    "hiddenpower": ["7M", "7V", "6M", "5M", "4M", "3M"],
    "hyperbeam": ["8M", "7M", "7V", "6M", "5M", "4M", "3M"],
    "hypervoice": ["8M", "7T", "6T", "5T"],
    "irontail": ["8M", "7T", "7V", "6T", "5T", "4M", "3M"],
    "laserfocus": ["7T"],
    "lastresort": [
      "8L55",
      "7T",
      "7L41",
      "6T",
      "6L41",
      "5T",
      "5L50",
      "4T",
      "4L50"
    ],
    "lightscreen": ["8M", "7M", "6M", "5M", "4M", "3M"],
    "magiccoat": ["7T", "6T", "5T", "4T"],
    "magicroom": ["8M", "7T", "6T", "5T"],
    "mimic": ["3T"],
    "morningsun": ["8L30", "7L33", "7V", "6L33", "5L71", "4L71", "3L52", "3S0"],
    "mudslap": ["7V", "4T", "3T"],
    "naturalgift": ["4M"],
    "nightmare": ["7V", "3T"],
    "payday": ["8M"],
    "powerswap": ["8M", "8L35", "7L45", "6L45", "5L78", "4L78"],
    "protect": ["8M", "7M", "7V", "6M", "5M", "4M", "3M"],
    "psybeam": ["8L25", "7L20", "7V", "6L20", "5L36", "4L36", "3L36", "3S0"],
    "psychic": [
      "8M",
      "8L40",
      "7M",
      "7L37",
      "7V",
      "7S3",
      "6M",
      "6L37",
      "5M",
      "5L64",
      "4M",
      "4L64",
      "3M",
      "3L47",
      "3S0"
    ],
    "psychicfangs": ["8M"],
    "psychup": [
      "8L45",
      "7M",
      "7L29",
      "7V",
      "6M",
      "6L29",
      "5M",
      "5L57",
      "4M",
      "4L57",
      "3T",
      "3L42",
      "3S0"
    ],
    "psyshock": ["8M", "7M", "6M", "5M"],
    "quickattack": ["8L10", "7L13", "7V", "6L13", "5L22", "4L22", "3L23"],
    "raindance": ["8M", "7M", "7V", "6M", "5M", "4M", "3M"],
    "reflect": ["8M", "7M", "7S3", "6M", "5M", "4M", "3M"],
    "rest": ["8M", "7M", "7V", "6M", "5M", "4M", "3M"],
    "retaliate": ["8M", "6M", "5M"],
    "return": ["7M", "7V", "6M", "5M", "4M", "3M"],
    "round": ["8M", "7M", "6M", "5M"],
    "sandattack": [
      "8L5",
      "7L5",
      "7V",
      "6L5",
      "6S2",
      "5L8",
      "5S1",
      "4L8",
      "3L8"
    ],
    "secretpower": ["6M", "4M", "3M"],
    "shadowball": ["8M", "7M", "7V", "7S3", "6M", "5M", "4M", "3M"],
    "signalbeam": ["7T", "6T", "5T", "4T"],
    "skillswap": ["8M", "7T", "6T", "5T", "4M", "3M"],
    "sleeptalk": ["8M", "7M", "7V", "6M", "5T", "4M", "3T"],
    "snore": ["8M", "7T", "7V", "6T", "5T", "4T", "3T"],
    "storedpower": ["8M"],
    "substitute": ["8M", "7M", "6M", "5M", "4M", "3T"],
    "sunnyday": ["8M", "7M", "7V", "6M", "5M", "4M", "3M"],
    "swagger": ["7M", "7V", "6M", "5M", "4M", "3T"],
    "swift": [
      "8M",
      "8L20",
      "7L17",
      "7V",
      "6L17",
      "5L29",
      "4T",
      "4L29",
      "3T",
      "3L30"
    ],
    "tackle": ["8L1", "7L1", "7V", "6L1", "5L1", "5S1", "4L1", "3L1"],
    "tailwhip": ["8L1", "7L1", "7V", "6L1", "6S2", "5L1", "5S1", "4L1", "3L1"],
    "takedown": ["8L1"],
    "telekinesis": ["7T", "5M"],
    "toxic": ["7M", "7V", "6M", "5M", "4M", "3M"],
    "trick": ["8M", "7T", "6T", "5T", "4T"],
    "trickroom": ["8M", "7M", "6M", "5M", "4M"],
    "weatherball": ["8M"],
    "workup": ["8M", "7M", "5M"],
    "zapcannon": ["7V"],
    "zenheadbutt": ["8M", "7T", "6T", "5T", "4T"]
  },
  "eventData": [
    {
      "generation": 3,
      "level": 70,
      "moves": ["psybeam", "psychup", "psychic", "morningsun"],
      "pokeball": "pokeball"
    },
    {
      "generation": 5,
      "level": 10,
      "gender": "M",
      "isHidden": true,
      "moves": ["tailwhip", "tackle", "helpinghand", "sandattack"]
    },
    {
      "generation": 6,
      "level": 10,
      "moves": ["celebrate", "tailwhip", "sandattack", "confusion"],
      "pokeball": "cherishball"
    },
    {
      "generation": 7,
      "level": 50,
      "gender": "F",
      "isHidden": true,
      "moves": ["psychic", "dazzlinggleam", "shadowball", "reflect"],
      "pokeball": "cherishball"
    }
  ],
  "encounters": [],
  "eventOnly": false
}
