{
  "pokemon": "fennekin",
  "learnset": {
    "attract": ["7M", "6M"],
    "confide": ["7M", "6M"],
    "covet": ["7T", "6T"],
    "cut": ["6M"],
    "doubleteam": ["7M", "6M"],
    "dreameater": ["7M", "6M"],
    "echoedvoice": ["7M", "6M"],
    "embargo": ["7M", "6M"],
    "ember": ["7L5", "6L5"],
    "facade": ["7M", "6M"],
    "fireblast": ["7M", "7L48", "6M", "6L48"],
    "firepledge": ["7T", "6T"],
    "firespin": ["7L20", "6L20"],
    "flamecharge": ["7M", "7L14", "6M", "6L14"],
    "flamethrower": ["7M", "7L35", "6M", "6L35", "6S0"],
    "foulplay": ["7T", "6T"],
    "frustration": ["7M", "6M"],
    "grassknot": ["7M", "6M"],
    "heatwave": ["7T", "7E", "6T", "6E"],
    "hiddenpower": ["7M", "6M", "6S0"],
    "howl": ["7L11", "6L11"],
    "hypnosis": ["7E", "6E"],
    "incinerate": ["6M"],
    "irontail": ["7T", "6T"],
    "lightscreen": ["7M", "7L27", "6M", "6L27"],
    "luckychant": ["7L25", "6L25"],
    "magiccoat": ["7T", "7E", "6T", "6E"],
    "magicroom": ["7T", "7L46", "6T", "6L46"],
    "overheat": ["7M", "6M"],
    "poweruppunch": ["6M"],
    "protect": ["7M", "6M"],
    "psybeam": ["7L17", "6L17"],
    "psychic": ["7M", "7L41", "6M", "6L41"],
    "psychicterrain": ["7E"],
    "psychup": ["7M", "6M"],
    "psyshock": ["7M", "7L31", "6M", "6L31"],
    "raindance": ["7M", "6M"],
    "rest": ["7M", "6M"],
    "return": ["7M", "6M"],
    "round": ["7M", "6M"],
    "safeguard": ["7M", "6M"],
    "scratch": ["7L1", "6L1", "6S0"],
    "secretpower": ["6M"],
    "sleeptalk": ["7M", "6M"],
    "snore": ["7T", "6T"],
    "solarbeam": ["7M", "6M"],
    "substitute": ["7M", "6M"],
    "sunnyday": ["7M", "7L43", "6M", "6L43"],
    "swagger": ["7M", "6M"],
    "tailwhip": ["7L1", "6L1"],
    "thief": ["7M", "6M"],
    "toxic": ["7M", "6M"],
    "willowisp": ["7M", "7L38", "6M", "6L38"],
    "wish": ["7E", "6E"],
    "workup": ["7M"]
  },
  "eventData": [
    {
      "generation": 6,
      "level": 15,
      "gender": "F",
      "nature": "Hardy",
      "moves": ["scratch", "flamethrower", "hiddenpower"],
      "pokeball": "cherishball"
    }
  ],
  "encounters": [],
  "eventOnly": false
}
