{
  "pokemon": "garbodor",
  "learnset": {
    "acidspray": ["8L1", "7L12", "6L12", "5L12"],
    "amnesia": ["8M", "8L9", "7L46", "6L46", "5L46"],
    "attract": ["8M", "7M", "6M", "5M"],
    "belch": ["8L33", "7L49", "6L49"],
    "bodypress": ["8M"],
    "bodyslam": ["8M", "8L24", "7L25", "6L25", "5L25"],
    "clearsmog": ["8L12", "7L34", "6L34", "5L34"],
    "confide": ["7M", "6M"],
    "corrosivegas": ["8T"],
    "crosspoison": ["8M"],
    "darkpulse": ["8M", "7M", "6M", "5T"],
    "doubleslap": ["7L14", "6L14", "5L14"],
    "doubleteam": ["7M", "6M", "5M"],
    "drainpunch": ["8M", "7T", "6T", "5T"],
    "endure": ["8M"],
    "explosion": ["8L48", "7M", "7L59", "6M", "6L59", "5M", "5L59"],
    "facade": ["8M", "7M", "6M", "5M"],
    "fling": ["8M", "7M", "6M", "5M"],
    "focusblast": ["8M", "7M", "6M", "5M"],
    "frustration": ["7M", "6M", "5M"],
    "gigadrain": ["8M", "7T", "6T", "5T"],
    "gigaimpact": ["8M", "7M", "6M", "5M"],
    "gunkshot": ["8M", "8L43", "7T", "7L54", "6T", "6L54", "5T", "5L54"],
    "hiddenpower": ["7M", "6M", "5M"],
    "hyperbeam": ["8M", "7M", "6M", "5M"],
    "infestation": ["7M", "6M"],
    "metalclaw": ["8L1"],
    "painsplit": ["8L39", "7T", "6T", "5T"],
    "payback": ["8M", "7M", "6M", "5M"],
    "poisongas": ["8L1", "7L1", "6L1", "5L1"],
    "pound": ["8L1", "7L1", "6L1", "5L1"],
    "protect": ["8M", "7M", "6M", "5M"],
    "psychic": ["8M", "7M", "6M", "5M"],
    "raindance": ["8M", "7M", "6M", "5M"],
    "recycle": ["8L1", "7T", "7L1", "6T", "6L1", "5T", "5L1"],
    "rest": ["8M", "7M", "6M", "5M"],
    "return": ["7M", "6M", "5M"],
    "rockblast": ["8M"],
    "rockpolish": ["7M", "6M", "5M"],
    "round": ["8M", "7M", "6M", "5M"],
    "screech": ["8M"],
    "secretpower": ["6M"],
    "seedbomb": ["8M", "7T", "6T", "5T"],
    "selfdestruct": ["8M"],
    "sleeptalk": ["8M", "7M", "6M", "5T"],
    "sludge": ["8L18", "7L18", "6L18", "5L18"],
    "sludgebomb": ["8M", "8L27", "7M", "7L29", "6M", "6L29", "5M", "5L29"],
    "sludgewave": ["8M", "7M", "6M", "5M"],
    "smackdown": ["7M", "6M", "5M"],
    "snore": ["8M", "7T", "6T", "5T"],
    "solarbeam": ["8M", "7M", "6M", "5M"],
    "spikes": ["8M"],
    "spite": ["7T", "6T", "5T"],
    "stockpile": ["8L21", "7L23", "6L23", "5L23"],
    "stompingtantrum": ["8M", "7T"],
    "substitute": ["8M", "7M", "6M", "5M"],
    "sunnyday": ["8M", "7M", "6M", "5M"],
    "swagger": ["7M", "6M", "5M"],
    "swallow": ["8L21", "7L23", "6L23", "5L23"],
    "takedown": ["8L1"],
    "thief": ["8M", "7M", "6M", "5M"],
    "thunderbolt": ["8M", "7M", "6M", "5M"],
    "toxic": ["8L30", "7M", "7L39", "6M", "6L39", "5M", "5L39"],
    "toxicspikes": ["8M", "8L15", "7L1", "6L1", "5L1"],
    "venomdrench": ["8M"],
    "venoshock": ["8M", "7M", "6M", "5M"]
  },
  "eventData": [],
  "encounters": [
    {
      "generation": 5,
      "level": 31
    },
    {
      "generation": 6,
      "level": 30
    },
    {
      "generation": 7,
      "level": 24
    }
  ],
  "eventOnly": false
}
