{
  "pokemon": "lunatone",
  "learnset": {
    "acrobatics": ["8M", "7M", "6M", "5M"],
    "allyswitch": ["8M", "7T"],
    "ancientpower": ["4T"],
    "batonpass": ["8M", "3S1"],
    "blizzard": ["8M", "7M", "6M", "5M", "4M"],
    "bodyslam": ["8M", "3T"],
    "bulldoze": ["8M", "7M", "6M", "5M"],
    "calmmind": ["8M", "7M", "6M", "5M", "4M", "3M"],
    "chargebeam": ["7M", "6M", "5M", "4M"],
    "confide": ["7M", "6M"],
    "confusion": ["8L1", "7L1", "6L1", "5L1", "5D", "4L1", "3L7", "3S0"],
    "cosmicpower": [
      "8M",
      "8L25",
      "7L25",
      "7S2",
      "6L25",
      "5L34",
      "4L34",
      "3L31"
    ],
    "defensecurl": ["3T"],
    "doubleedge": ["3T"],
    "doubleteam": ["7M", "6M", "5M", "4M", "3M"],
    "dreameater": ["7M", "6M", "5M", "4M", "3T"],
    "earthpower": ["8M", "7T", "6T", "5T", "5D", "4T"],
    "earthquake": ["8M", "7M", "6M", "5M", "4M", "3M"],
    "embargo": ["7M", "7L17", "6M", "6L17", "5M", "5L31", "4M", "4L31"],
    "endure": ["8M", "4M", "3T"],
    "explosion": [
      "8L50",
      "7M",
      "7L45",
      "6M",
      "6L45",
      "5M",
      "5L56",
      "4M",
      "4L56",
      "3T",
      "3L49"
    ],
    "facade": ["8M", "7M", "6M", "5M", "4M", "3M"],
    "flash": ["6M", "5M", "4M", "3M"],
    "frustration": ["7M", "6M", "5M", "4M", "3M"],
    "futuresight": ["8M", "8L40", "7L41", "6L41", "5L53", "4L53", "3L43"],
    "gigaimpact": ["8M", "7M", "6M", "5M", "4M"],
    "grassknot": ["8M", "7M", "6M", "5M", "4M"],
    "gravity": ["7T", "6T", "5T", "4T"],
    "gyroball": ["8M", "7M", "6M", "5M", "4M"],
    "hail": ["8M"],
    "harden": ["8L1", "7L1", "6L1", "5L1", "4L1", "3L1", "3S0"],
    "healblock": ["7L33", "6L33", "5L42", "4L42"],
    "helpinghand": ["8M", "7T", "6T", "5T", "4T"],
    "hiddenpower": ["7M", "7S2", "6M", "5M", "4M", "3M"],
    "hyperbeam": ["8M", "7M", "6M", "5M", "4M", "3M"],
    "hypnosis": ["8L5", "7L5", "6L5", "5L12", "4L12", "3L19"],
    "icebeam": ["8M", "7M", "6M", "5M", "4M", "3M"],
    "icywind": ["8M", "7T", "6T", "5T"],
    "ironhead": ["8M", "7T", "6T", "5T", "4T"],
    "laserfocus": ["7T"],
    "lightscreen": ["8M", "7M", "6M", "5M", "4M", "3M"],
    "magiccoat": ["7T", "6T", "5T", "4T"],
    "magicroom": ["8M", "8L45", "7T", "7L49", "6T", "6L1", "5T", "5L64"],
    "meteorbeam": ["8T"],
    "mimic": ["3T"],
    "moonblast": ["8L1", "7L1", "7S2", "6L1"],
    "moonlight": ["8L1", "5D"],
    "nastyplot": ["8M"],
    "naturalgift": ["4M"],
    "painsplit": ["7T", "6T", "5T", "4T"],
    "powergem": ["8M", "7L1", "7S2"],
    "powerswap": ["8M"],
    "protect": ["8M", "7M", "6M", "5M", "4M", "3M"],
    "psychic": [
      "8M",
      "8L30",
      "7M",
      "7L29",
      "6M",
      "6L29",
      "5M",
      "5L45",
      "4M",
      "4L45",
      "3M",
      "3L37",
      "3S1"
    ],
    "psychicterrain": ["8M"],
    "psychup": ["7M", "6M", "5M", "4M", "3T"],
    "psyshock": ["8M", "8L20", "7M", "7L1", "6M", "5M"],
    "psywave": ["7L13", "6L13", "5L23", "4L23", "3L25"],
    "raindance": ["8M", "7M", "6M", "5M", "4M", "3M", "3S1"],
    "recycle": ["7T", "6T", "5T", "4M"],
    "reflect": ["8M", "7M", "6M", "5M", "4M", "3M"],
    "rest": ["8M", "7M", "6M", "5M", "4M", "3M"],
    "return": ["7M", "6M", "5M", "4M", "3M"],
    "rockblast": ["8M"],
    "rockpolish": [
      "8L10",
      "7M",
      "7L9",
      "6M",
      "6L9",
      "5M",
      "5L20",
      "4M",
      "4L20"
    ],
    "rockslide": [
      "8M",
      "8L15",
      "7M",
      "7L21",
      "6M",
      "6L21",
      "5M",
      "5L25",
      "4M",
      "3T"
    ],
    "rockthrow": ["8L1", "7L1", "6L1", "5L9", "4L9", "3L13"],
    "rocktomb": ["8M", "7M", "6M", "5M", "4M", "3M", "3S1"],
    "rollout": ["4T", "3T"],
    "round": ["8M", "7M", "6M", "5M"],
    "safeguard": ["8M", "7M", "6M", "5M", "4M", "3M"],
    "sandstorm": ["8M", "7M", "6M", "5M", "4M", "3M"],
    "sandtomb": ["8M"],
    "secretpower": ["6M", "4M", "3M"],
    "selfdestruct": ["8M", "3T"],
    "shadowball": ["8M", "7M", "6M", "5M", "4M", "3M"],
    "signalbeam": ["7T", "6T", "5T", "4T"],
    "skillswap": ["8M", "7T", "6T", "5T", "4M", "3M"],
    "sleeptalk": ["8M", "7M", "6M", "5T", "4M", "3T"],
    "smackdown": ["7M", "6M", "5M"],
    "snore": ["8M", "7T", "6T", "5T", "4T", "3T"],
    "stealthrock": ["8M", "7T", "6T", "5T", "4M"],
    "stompingtantrum": ["8M", "7T"],
    "stoneedge": ["8M", "8L35", "7M", "7L37", "6M", "6L37", "5M", "5L41", "4M"],
    "storedpower": ["8M"],
    "substitute": ["8M", "7M", "6M", "5M", "4M", "3T"],
    "swagger": ["7M", "6M", "5M", "4M", "3T"],
    "swift": ["8M", "4T", "3T"],
    "tackle": ["8L1", "7L1", "6L1", "5L1", "4L1", "3L1", "3S0"],
    "telekinesis": ["7T", "5M"],
    "toxic": ["7M", "6M", "5M", "4M", "3M"],
    "trickroom": ["8M", "7M", "6M", "5M", "4M"],
    "weatherball": ["8M"],
    "zenheadbutt": ["8M", "7T", "6T", "5T", "4T"]
  },
  "eventData": [
    {
      "generation": 3,
      "level": 10,
      "moves": ["tackle", "harden", "confusion"],
      "pokeball": "pokeball"
    },
    {
      "generation": 3,
      "level": 25,
      "moves": ["batonpass", "psychic", "raindance", "rocktomb"]
    },
    {
      "generation": 7,
      "level": 30,
      "moves": ["cosmicpower", "hiddenpower", "moonblast", "powergem"],
      "pokeball": "cherishball"
    }
  ],
  "encounters": [],
  "eventOnly": false
}
