{
  "pokemon": "lurantistotem",
  "learnset": {
    "aerialace": ["7M"],
    "attract": ["7M"],
    "brickbreak": ["7M"],
    "bugbite": ["7T"],
    "confide": ["7M"],
    "defog": ["7T"],
    "doubleteam": ["7M"],
    "dualchop": ["7T"],
    "energyball": ["7M"],
    "facade": ["7M"],
    "falseswipe": ["7M"],
    "fling": ["7M"],
    "frustration": ["7M"],
    "furycutter": ["7L1"],
    "gigadrain": ["7T"],
    "gigaimpact": ["7M"],
    "grassknot": ["7M"],
    "growth": ["7L1", "7S0"],
    "hiddenpower": ["7M"],
    "hyperbeam": ["7M"],
    "ingrain": ["7L19", "7S0"],
    "knockoff": ["7T"],
    "laserfocus": ["7T"],
    "leafage": ["7L1"],
    "leafblade": ["7L23", "7S0"],
    "leechlife": ["7M"],
    "lowsweep": ["7M"],
    "naturepower": ["7M"],
    "nightslash": ["7L1"],
    "payback": ["7M"],
    "petalblizzard": ["7L1"],
    "poisonjab": ["7M"],
    "protect": ["7M"],
    "razorleaf": ["7L1"],
    "rest": ["7M"],
    "return": ["7M"],
    "round": ["7M"],
    "safeguard": ["7M"],
    "seedbomb": ["7T"],
    "signalbeam": ["7T"],
    "slash": ["7L32"],
    "sleeptalk": ["7M"],
    "snore": ["7T"],
    "solarbeam": ["7M"],
    "solarblade": ["7L47"],
    "substitute": ["7M"],
    "sunnyday": ["7M", "7L55"],
    "superpower": ["7T"],
    "swagger": ["7M"],
    "sweetscent": ["7L40"],
    "swordsdance": ["7M"],
    "synthesis": ["7T", "7L28", "7S0"],
    "toxic": ["7M"],
    "worryseed": ["7T"],
    "xscissor": ["7M", "7L1"]
  },
  "eventData": [
    {
      "generation": 7,
      "level": 30,
      "perfectIVs": 3,
      "moves": ["growth", "ingrain", "leafblade", "synthesis"],
      "pokeball": "pokeball"
    }
  ],
  "encounters": [],
  "eventOnly": true
}
