{
  "pokemon": "mienfoo",
  "learnset": {
    "acrobatics": ["8M", "7M", "6M", "5M"],
    "aerialace": ["7M", "6M", "5M"],
    "agility": ["8M"],
    "allyswitch": ["8M", "7T", "7E", "6E"],
    "attract": ["8M", "7M", "6M", "5M"],
    "aurasphere": ["8M", "8L45", "7L61", "6L61", "5L61"],
    "batonpass": ["8M", "7E", "6E", "5E"],
    "bounce": ["8M", "8L51", "7T", "7L49", "6T", "6L49", "5T", "5L49"],
    "brickbreak": ["8M", "7M", "6M", "5M"],
    "bulkup": ["8M", "7M", "6M", "5M"],
    "calmmind": ["8M", "8L55", "7M", "7L25", "6M", "6L25", "5M", "5L25"],
    "closecombat": ["8M"],
    "coaching": ["8T"],
    "confide": ["7M", "6M"],
    "detect": ["8L1", "7L9", "6L9", "5L9"],
    "dig": ["8M", "6M", "5M"],
    "doubleslap": ["7L17", "6L17", "5L17"],
    "doubleteam": ["7M", "6M", "5M"],
    "drainpunch": ["8M", "8L35", "7T", "7L33", "6T", "6L33", "5T", "5L33"],
    "dualchop": ["7T", "6T", "5T"],
    "endure": ["8M", "7E", "6E", "5E"],
    "facade": ["8M", "7M", "6M", "5M"],
    "fakeout": ["8L5", "7L13", "6L13", "5L13"],
    "feint": ["8E", "7E", "6E", "5E"],
    "fling": ["8M", "7M", "6M", "5M"],
    "focusblast": ["8M", "7M", "6M", "5M"],
    "focusenergy": ["8M"],
    "focuspunch": ["8E", "7T", "6T"],
    "forcepalm": ["8L25", "7L29", "6L29", "5L29"],
    "frustration": ["7M", "6M", "5M"],
    "furyswipes": ["8L15"],
    "grassknot": ["8M", "7M", "6M", "5M"],
    "helpinghand": ["8M", "7T", "6T", "5T"],
    "hiddenpower": ["7M", "6M", "5M"],
    "highjumpkick": ["8L60", "7L50", "6L50", "5L53"],
    "honeclaws": ["8L40"],
    "jumpkick": ["7L37", "6L37", "5L37"],
    "knockoff": ["8E", "7T", "7E", "6T", "6E", "5T", "5E"],
    "lowkick": ["8M", "7T", "7E", "6T", "6E", "5T", "5E"],
    "lowsweep": ["8M", "7M", "6M", "5M"],
    "meditate": ["7L5", "6L5", "5L5"],
    "mefirst": ["7E", "6E", "5E"],
    "megakick": ["8M"],
    "megapunch": ["8M"],
    "payback": ["8M", "7M", "6M", "5M"],
    "poisonjab": ["8M", "7M", "6M", "5M"],
    "pound": ["8L1", "7L1", "6L1", "5L1"],
    "poweruppunch": ["6M"],
    "protect": ["8M", "7M", "6M", "5M"],
    "psychup": ["7M", "6M", "5M"],
    "quickguard": ["8L20", "7L45", "6L45", "5L45"],
    "raindance": ["8M", "7M", "6M", "5M"],
    "reflect": ["8M", "7M", "6M", "5M"],
    "rest": ["8M", "7M", "6M", "5M"],
    "retaliate": ["8M", "6M", "5M"],
    "return": ["7M", "6M", "5M"],
    "revenge": ["8M"],
    "reversal": ["8M", "8L10", "7L57", "6L57", "5L57"],
    "rockslide": ["8M", "7M", "6M", "5M"],
    "rocksmash": ["6M", "5M"],
    "rocktomb": ["8M", "7M", "6M", "5M"],
    "roleplay": ["7T", "6T", "5T"],
    "round": ["8M", "7M", "6M", "5M"],
    "secretpower": ["6M"],
    "sleeptalk": ["8M", "7M", "6M", "5T"],
    "smellingsalts": ["7E", "6E", "5E"],
    "snore": ["8M", "7T", "6T", "5T"],
    "stoneedge": ["8M", "7M", "6M", "5M"],
    "strength": ["6M", "5M"],
    "substitute": ["8M", "7M", "6M", "5M"],
    "sunnyday": ["8M", "7M", "6M", "5M"],
    "swagger": ["7M", "6M", "5M"],
    "swift": ["8M", "7L21", "6L21", "5L21"],
    "swordsdance": ["8M", "7M", "6M", "5M"],
    "taunt": ["8M", "7M", "6M", "5M"],
    "toxic": ["7M", "6M", "5M"],
    "uturn": ["8M", "8L30", "7M", "7L41", "6M", "6L41", "5M", "5L41"],
    "vitalthrow": ["8E", "7E", "6E", "5E"],
    "workup": ["8M", "7M", "5M"]
  },
  "eventData": [],
  "encounters": [],
  "eventOnly": false
}
