{
  "pokemon": "raticatealolatotem",
  "learnset": {
    "assurance": ["7L19", "7S0"],
    "attract": ["7M"],
    "bite": ["7L10", "7S0"],
    "blizzard": ["7M"],
    "bulkup": ["7M"],
    "confide": ["7M"],
    "covet": ["7T"],
    "crunch": ["7L24"],
    "darkpulse": ["7M"],
    "doubleedge": ["7L39"],
    "doubleteam": ["7M"],
    "embargo": ["7M"],
    "endeavor": ["7T", "7L44"],
    "facade": ["7M"],
    "focusenergy": ["7L1"],
    "frustration": ["7M"],
    "gigaimpact": ["7M"],
    "grassknot": ["7M"],
    "hiddenpower": ["7M"],
    "hyperbeam": ["7M"],
    "hyperfang": ["7L16", "7S0"],
    "icebeam": ["7M"],
    "icywind": ["7T"],
    "irontail": ["7T"],
    "knockoff": ["7T"],
    "lastresort": ["7T"],
    "protect": ["7M"],
    "pursuit": ["7L13", "7S0"],
    "quash": ["7M"],
    "quickattack": ["7L1"],
    "raindance": ["7M"],
    "rest": ["7M"],
    "return": ["7M"],
    "roar": ["7M"],
    "round": ["7M"],
    "scaryface": ["7L1"],
    "shadowball": ["7M"],
    "shadowclaw": ["7M"],
    "shockwave": ["7T"],
    "sleeptalk": ["7M"],
    "sludgebomb": ["7M"],
    "sludgewave": ["7M"],
    "snarl": ["7M"],
    "snatch": ["7T"],
    "snore": ["7T"],
    "stompingtantrum": ["7T"],
    "substitute": ["7M"],
    "suckerpunch": ["7L29"],
    "sunnyday": ["7M"],
    "superfang": ["7T", "7L34"],
    "swagger": ["7M"],
    "swordsdance": ["7M", "7L1"],
    "tackle": ["7L1"],
    "tailwhip": ["7L1"],
    "taunt": ["7M"],
    "thief": ["7M"],
    "throatchop": ["7T"],
    "torment": ["7M"],
    "toxic": ["7M"],
    "uproar": ["7T"],
    "uturn": ["7M"],
    "venoshock": ["7M"],
    "zenheadbutt": ["7T"]
  },
  "eventData": [
    {
      "generation": 7,
      "level": 20,
      "perfectIVs": 3,
      "moves": ["bite", "pursuit", "hyperfang", "assurance"],
      "pokeball": "pokeball"
    }
  ],
  "encounters": [],
  "eventOnly": true
}
