{
  "pokemon": "shaymin",
  "learnset": {
    "aircutter": ["4T"],
    "airslash": ["7L64", "6L64", "6S3", "5L64", "4L64"],
    "aromatherapy": ["7L64", "6L64", "6S4", "5L64", "4L64", "4S0"],
    "bulletseed": ["4M"],
    "celebrate": ["7S5"],
    "confide": ["7M", "6M"],
    "covet": ["7T", "6T", "5T"],
    "dazzlinggleam": ["7M", "6M"],
    "defensecurl": ["4L1"],
    "doubleteam": ["7M", "6M", "5M", "4M"],
    "earthpower": ["7T", "6T", "5T", "4T"],
    "endeavor": ["7T", "6T", "5T", "4T"],
    "endure": ["4M"],
    "energyball": [
      "7M",
      "7L73",
      "6M",
      "6L73",
      "6S4",
      "5M",
      "5L73",
      "4M",
      "4L73",
      "4S0"
    ],
    "facade": ["7M", "6M", "5M", "4M"],
    "flash": ["6M", "5M", "4M"],
    "frustration": ["7M", "6M", "5M", "4M"],
    "gigadrain": ["7T", "6T", "5T", "4M"],
    "gigaimpact": ["7M", "6M", "5M", "4M"],
    "grassknot": ["7M", "6M", "5M", "4M"],
    "grasswhistle": ["4L82"],
    "growth": ["7L1", "7S5", "6L1", "6S3", "5L1", "4L1", "4S1"],
    "headbutt": ["4T"],
    "healingwish": ["7L91", "6L91", "5L91", "4L91"],
    "hiddenpower": ["7M", "6M", "5M", "4M"],
    "hyperbeam": ["7M", "6M", "5M", "4M"],
    "laserfocus": ["7T"],
    "lastresort": ["7T", "6T", "5T", "4T"],
    "leafstorm": ["7L91", "6L91", "5L91", "4L91"],
    "leechseed": ["7L19", "6L19", "5L19", "5S2", "4L19", "4S1"],
    "luckychant": ["4L91"],
    "magicalleaf": ["7L10", "6L10", "6S3", "5L10", "4L10", "4S1"],
    "mudslap": ["4T"],
    "naturalgift": ["7L46", "6L46", "5L46", "4M", "4L46"],
    "naturepower": ["7M", "6M"],
    "ominouswind": ["4T"],
    "protect": ["7M", "6M", "5M", "4M"],
    "psychic": ["7M", "6M", "5M", "4M"],
    "psychup": ["7M", "6M", "5M", "4M"],
    "quickattack": ["7L28", "6L28", "5L28", "4L28"],
    "rest": ["7M", "6M", "5M", "4M"],
    "return": ["7M", "7S5", "6M", "5M", "4M"],
    "round": ["7M", "6M", "5M"],
    "safeguard": ["7M", "6M", "5M", "4M"],
    "secretpower": ["6M", "4M"],
    "seedbomb": ["7T", "6T", "5T", "4T"],
    "seedflare": [
      "7L100",
      "7S5",
      "6L100",
      "6S3",
      "6S4",
      "5L100",
      "5S2",
      "4L100",
      "4S0"
    ],
    "sleeptalk": ["7M", "6M", "5T", "4M"],
    "snore": ["7T", "6T", "5T", "4T"],
    "solarbeam": ["7M", "6M", "5M", "4M"],
    "substitute": ["7M", "6M", "6S4", "5M", "4M", "4S0"],
    "sunnyday": ["7M", "6M", "5M", "4M"],
    "swagger": ["7M", "6M", "5M", "4M"],
    "sweetkiss": ["7L82", "6L82", "5L82", "4L82"],
    "sweetscent": ["7L37", "6L37", "5L37", "5S2", "4L37"],
    "swift": ["4T"],
    "swordsdance": ["7M", "6M", "5M", "4M"],
    "synthesis": [
      "7T",
      "7L28",
      "6T",
      "6L28",
      "5T",
      "5L28",
      "5S2",
      "4T",
      "4L28",
      "4S1"
    ],
    "tailwind": ["7T", "6T", "5T", "4T"],
    "toxic": ["7M", "6M", "5M", "4M"],
    "worryseed": ["7T", "7L55", "6T", "6L55", "5T", "5L55", "4T", "4L55"],
    "zenheadbutt": ["7T", "6T", "5T", "4T"]
  },
  "eventData": [
    {
      "generation": 4,
      "level": 50,
      "moves": ["seedflare", "aromatherapy", "substitute", "energyball"],
      "pokeball": "cherishball"
    },
    {
      "generation": 4,
      "level": 30,
      "shiny": 1,
      "moves": ["growth", "magicalleaf", "leechseed", "synthesis"],
      "pokeball": "pokeball"
    },
    {
      "generation": 5,
      "level": 50,
      "moves": ["seedflare", "leechseed", "synthesis", "sweetscent"],
      "pokeball": "cherishball"
    },
    {
      "generation": 6,
      "level": 15,
      "moves": ["growth", "magicalleaf", "seedflare", "airslash"],
      "pokeball": "cherishball"
    },
    {
      "generation": 6,
      "level": 100,
      "moves": ["seedflare", "aromatherapy", "substitute", "energyball"],
      "pokeball": "cherishball"
    },
    {
      "generation": 7,
      "level": 20,
      "moves": ["return", "growth", "seedflare", "celebrate"],
      "pokeball": "cherishball"
    }
  ],
  "encounters": [],
  "eventOnly": true
}
